goodok_mlu/__init__.py
goodok_mlu/io.py
goodok_mlu/log.py
goodok_mlu/model.py
goodok_mlu/summary.py
goodok_mlu/utils.py
goodok_mlu/version.py
goodok_mlu/kekas/__init__.py
goodok_mlu/kekas/callbacks/__init__.py
goodok_mlu/kekas/callbacks/kekas_annealing_cos.py
goodok_mlu/kekas/callbacks/neptune_callbacks.py
goodok_mlu/kekas/callbacks/tb_logger.py
goodok_mlu/optimizers/__init__.py
goodok_mlu/optimizers/radam.py
goodok_mlu/trackers/__init__.py
goodok_mlu/trackers/neptune.py
goodok_mlu/trackers/visualize/__init__.py
goodok_mlu/trackers/visualize/utils.py
goodok_mlu-0.0.3.dist-info/LICENSE
goodok_mlu-0.0.3.dist-info/METADATA
goodok_mlu-0.0.3.dist-info/WHEEL
goodok_mlu-0.0.3.dist-info/top_level.txt
goodok_mlu-0.0.3.dist-info/RECORD
