Metadata-Version: 2.1
Name: goodok-mlu
Version: 0.0.3
Summary: Common ML utils
Home-page: https://github.com/goodok/ml_utils
Author: Alexey U. Gudchenko
Author-email: proga@goodok.ru
License: UNKNOWN
Platform: UNKNOWN
Requires-Python: >=3.6
License-File: LICENSE
